q2_itsxpress/__init__.py
q2_itsxpress/_itsxpress.py
q2_itsxpress/citations.bib
q2_itsxpress/plugin_setup.py
q2_itsxpress-1.8.1.dist-info/LICENSE.txt
q2_itsxpress-1.8.1.dist-info/METADATA
q2_itsxpress-1.8.1.dist-info/WHEEL
q2_itsxpress-1.8.1.dist-info/entry_points.txt
q2_itsxpress-1.8.1.dist-info/top_level.txt
q2_itsxpress-1.8.1.dist-info/RECORD
