Metadata-Version: 2.1
Name: q2-itsxpress
Version: 1.8.1
Summary: A QIIME2 plugin to trim ITS regions using ITSxpress
Author-email: "Adam R. Rivers" <adam.rivers@usda.gov>, "Sveinn V. Einarsson" <seinarsson@ufl.edu>
Maintainer-email: "Adam R. Rivers" <adam.rivers@usda.gov>, "Sveinn V. Einarsson" <seinarsson@ufl.edu>
License: Creative Commons Legal Code CC0 1.0 Universal Official translations of this
Project-URL: repository, http://github.com/usda-ars-gbru/q2_itsxpress
Keywords: Qiime2,plugin,Amplicon,sequencing,fungal,ITS
Classifier: Topic :: Scientific/Engineering :: Bio-Informatics
Classifier: Programming Language :: Python :: 3.8
Classifier: Development Status :: 7 - Inactive
Requires-Python: >=3.8
License-File: LICENSE.txt
Requires-Dist: qiime2
Requires-Dist: itsxpress (>=1.8.1)
Requires-Dist: pandas
Provides-Extra: tests
Requires-Dist: pytest ; extra == 'tests'
